{
    "location": {
        "city": "Lisbon",
        "coordinates": {
            "latitude": 38.7697814,
            "longitude": -9.1001402
        },
        "country": "Portugal",
        "timezone": "Europe/Lisbon",
        "utcOffset": 1
    },
    "moderators": [
        {
            "name": "Bruno Santos",
            "url": "https://twitter.com/i3r41n"
        },
        {
            "name": "Jivago Alves",
            "url": "https://twitter.com/jivagoalves"
        },
        {
            "name": "Nuno Marques",
            "url": "https://twitter.com/nfma"
        }
    ],
    "sponsors": [
        {
            "name": "EqualExpertsPortugal",
            "url": "https://twitter.com/EE_Portugal"
        }
    ],
    "title": "Coderetreat 2017 in Lisbon",
    "url": "https://www.meetup.com/expert-talks-portugal/events/244654861/"
}
