{
    "location": {
        "city": "Utrecht",
        "coordinates": {
            "latitude": 52.0907,
            "longitude": 5.1214
        },
        "country": "Netherlands",
        "timezone": "Europe/Amsterdam",
        "utcOffset": 2
    },
    "moderators": [
        {
            "name": "Thodoris Bais",
            "url": "https://twitter.com/ThodorisBais"
        },
        {
            "name": "Patrick",
            "url": "https://twitter.com/pvdissel"
        },
        {
            "name": "Joost Baas"
        }
    ],
    "sponsors": [
        {
            "name": "bol.com",
            "url": "https://twitter.com/bol_com"
        }
    ],
    "title": "Global Day of Code Retreat - Utrecht 2017",
    "url": "https://www.meetup.com/Utrecht-Java-User-Group/events/243847568/"
}
