{"title":"Code Retreat Valence","url":"https://www.meetup.com/Ardech-Drom-Dev/events/266268740/","moderators":[{"name":"Gaspard POINTEAU","url":"https://twitter.com/Gaspard_PO"},{"name":"Camille Baronnet","url":"https://twitter.com/camillebaronnet"}],"sponsors":[{"name":"Winzana","url":"https://www.winzana.com/"}],"date":{"start":"2019-11-16T09:00:00.000+01:00","end":"2019-11-16T17:00:00.000+01:00"},"location":{"city":"Valence","country":"France","coordinates":{"latitude":44.9328158,"longitude":4.8887694}},"spoken_language":""}
